{
  "raceId": "1751544318",
  "racePda": "HLqbDSKshv2UHM7RgcfmUPpp1KSyaGBsBNUDzJtExpBH",
  "raceVaultPda": "J6L8heq5jUMfxYFMS48rkCLz7WPvNfrc5psJRFRv917B",
  "creator": "GsWeXfqrmGLkN3fFUu5bdoDPDWJLf5LzAWjNfvctLuA6",
  "maxPlayers": 100,
  "waitTime": 120,
  "referralCode": "U8OTYS00",
  "startTime": 1751544319,
  "horseNames": [
    "Step",
    "Tulip",
    "Marinade",
    "Phantom",
    "Francium",
    "Hubble",
    "Mango",
    "Saber",
    "Bonk",
    "Bonfida"
  ],
  "timestamp": "2025-07-03T12:05:22.132Z"
}